alm_core/__init__.py
alm_core/agent.py
alm_core/controller.py
alm_core/llm_client.py
alm_core/memory.py
alm_core/policy.py
alm_core/research.py
alm_core/visualizer.py
alm_core/tools/__init__.py
alm_core/tools/browser.py
alm_core/tools/desktop.py
alm_core-0.1.0.dist-info/licenses/LICENSE
alm_core-0.1.0.dist-info/METADATA
alm_core-0.1.0.dist-info/WHEEL
alm_core-0.1.0.dist-info/top_level.txt
alm_core-0.1.0.dist-info/RECORD
