Metadata-Version: 2.4
Name: alm-core
Version: 0.1.0
Summary: Agent Language Model (ALM): A deterministic, policy-driven architecture for robust AI agents
Home-page: https://github.com/Jalendar10/alm-core
Author: Jalendar Reddy Maligireddy
Author-email: Jalendar Reddy Maligireddy <jalendarreddy97@gmail.com>
License: MIT
Project-URL: Homepage, https://github.com/Jalendar10/alm-core
Project-URL: Documentation, https://github.com/Jalendar10/alm-core
Project-URL: Repository, https://github.com/Jalendar10/alm-core
Project-URL: Bug Reports, https://github.com/Jalendar10/alm-core/issues
Keywords: ai,agent,llm,automation,policy,privacy,security
Classifier: Development Status :: 3 - Alpha
Classifier: Intended Audience :: Developers
Classifier: Intended Audience :: Science/Research
Classifier: Topic :: Scientific/Engineering :: Artificial Intelligence
Classifier: License :: OSI Approved :: MIT License
Classifier: Programming Language :: Python :: 3
Classifier: Programming Language :: Python :: 3.8
Classifier: Programming Language :: Python :: 3.9
Classifier: Programming Language :: Python :: 3.10
Classifier: Programming Language :: Python :: 3.11
Requires-Python: >=3.8
License-File: LICENSE
Requires-Dist: openai>=1.0.0
Requires-Dist: anthropic>=0.7.0
Requires-Dist: networkx>=3.0
Requires-Dist: requests>=2.28.0
Provides-Extra: full
Requires-Dist: playwright>=1.40.0; extra == "full"
Requires-Dist: matplotlib>=3.5.0; extra == "full"
Requires-Dist: pyperclip>=1.8.0; extra == "full"
Requires-Dist: pyautogui>=0.9.50; extra == "full"
Requires-Dist: psutil>=5.9.0; extra == "full"
Provides-Extra: dev
Requires-Dist: pytest>=7.0.0; extra == "dev"
Requires-Dist: pytest-cov>=4.0.0; extra == "dev"
Requires-Dist: black>=22.0.0; extra == "dev"
Requires-Dist: flake8>=5.0.0; extra == "dev"
Requires-Dist: mypy>=1.0.0; extra == "dev"
Dynamic: author
Dynamic: home-page
Dynamic: license-file
Dynamic: requires-python
